intela_unibot-1.0.1.dist-info/licenses/AUTHORS.txt
intela_unibot-1.0.1.dist-info/licenses/LICENSE.txt
uni_bot/__init__.py
uni_bot/admin.py
uni_bot/apps.py
uni_bot/configuration_helpers.py
uni_bot/constants.py
uni_bot/data_collectors.py
uni_bot/decorators.py
uni_bot/enums.py
uni_bot/handlers.py
uni_bot/models.py
uni_bot/serializers.py
uni_bot/services.py
uni_bot/tab.py
uni_bot/tasks.py
uni_bot/urls.py
uni_bot/utils.py
uni_bot/api/__init__.py
uni_bot/api/client.py
uni_bot/api/permissions.py
uni_bot/api/routers.py
uni_bot/api/serializers.py
uni_bot/api/urls.py
uni_bot/api/views/__init__.py
uni_bot/api/views/additional_content.py
uni_bot/api/views/bot_status.py
uni_bot/api/views/course_context.py
uni_bot/api/views/course_users.py
uni_bot/api/views/course_widget_control.py
uni_bot/api/views/learning_models.py
uni_bot/api/views/restricted_questions.py
uni_bot/api/views/teacher_assistant_settings.py
uni_bot/api/views/widget.py
uni_bot/frontend-app/.eslintrc.cjs
uni_bot/frontend-app/commitlint.config.js
uni_bot/frontend-app/index.html
uni_bot/frontend-app/removeIndexHtml.js
uni_bot/frontend-app/vite.config.js
uni_bot/frontend-app/dist/uni_bot/assistance-feedback.png
uni_bot/frontend-app/dist/uni_bot/assistance-languages-summary.png
uni_bot/frontend-app/dist/uni_bot/assistance-ranking.png
uni_bot/frontend-app/dist/uni_bot/assistance-timing.png
uni_bot/frontend-app/dist/uni_bot/assistant-avatar.png
uni_bot/frontend-app/dist/uni_bot/bundle.js
uni_bot/frontend-app/dist/uni_bot/course-assistance-summary.png
uni_bot/frontend-app/dist/uni_bot/icon.png
uni_bot/frontend-app/dist/uni_bot/index.css
uni_bot/frontend-app/dist/uni_bot/performance-information.png
uni_bot/frontend-app/dist/uni_bot/the-most-popular-topics.png
uni_bot/frontend-app/public/icon.png
uni_bot/frontend-app/src/theme.js
uni_bot/frontend-app/src/utils.js
uni_bot/frontend-app/src/api/additionalContentSlice.js
uni_bot/frontend-app/src/api/apiSlice.js
uni_bot/frontend-app/src/api/botStatusesSlice.js
uni_bot/frontend-app/src/api/constants.js
uni_bot/frontend-app/src/api/courseContentSlice.js
intela_unibot-1.0.1.dist-info/METADATA
intela_unibot-1.0.1.dist-info/WHEEL
intela_unibot-1.0.1.dist-info/entry_points.txt
intela_unibot-1.0.1.dist-info/top_level.txt
intela_unibot-1.0.1.dist-info/RECORD
