Metadata-Version: 2.4
Name: intela-unibot
Version: 1.0.1
Summary: edX plugin for Uni Bot setup
Author: Intela
Author-email: info@intela.io
License: AGPL
Classifier: Development Status :: 5 - Production/Stable
Classifier: Framework :: Django :: 4.2
Classifier: Intended Audience :: Developers
Classifier: License :: OSI Approved :: GNU Affero General Public License v3
Classifier: Operating System :: OS Independent
Classifier: Programming Language :: Python :: 3.11
License-File: LICENSE.txt
License-File: AUTHORS.txt
Requires-Dist: amqp==5.3.1
Requires-Dist: appdirs==1.4.4
Requires-Dist: asgiref==3.9.1
Requires-Dist: attrs==25.3.0
Requires-Dist: beautifulsoup4==4.13.4
Requires-Dist: billiard==4.2.1
Requires-Dist: cachetools==6.1.0
Requires-Dist: celery==5.5.3
Requires-Dist: certifi==2025.7.14
Requires-Dist: cffi==1.17.1
Requires-Dist: chardet==5.2.0
Requires-Dist: charset-normalizer==2.0.12
Requires-Dist: click==8.2.1
Requires-Dist: click-didyoumean==0.3.1
Requires-Dist: click-plugins==1.1.1.2
Requires-Dist: click-repl==0.3.0
Requires-Dist: code-annotations==2.3.0
Requires-Dist: cryptography==45.0.5
Requires-Dist: django==4.2.23
Requires-Dist: django-config-models==2.9.0
Requires-Dist: django-countries==7.6.1
Requires-Dist: django-crum==0.7.9
Requires-Dist: django-model-utils==5.0.0
Requires-Dist: django-storages==1.14.3
Requires-Dist: django-waffle==5.0.0
Requires-Dist: djangorestframework==3.14.0
Requires-Dist: dnspython==2.7.0
Requires-Dist: drf-jwt==1.19.2
Requires-Dist: edx-ccx-keys==2.0.2
Requires-Dist: edx-django-release-util==1.5.0
Requires-Dist: edx-django-utils==8.0.0
Requires-Dist: edx-drf-extensions==10.6.0
Requires-Dist: edx-opaque-keys[django]==3.0.0
Requires-Dist: edx-toggles==5.3.0
Requires-Dist: edxval==3.0.0
Requires-Dist: fastavro==1.11.1
Requires-Dist: fs==2.4.16
Requires-Dist: idna==3.10
Requires-Dist: jinja2==3.1.6
Requires-Dist: jsonfield==3.2.0
Requires-Dist: kombu==5.5.4
Requires-Dist: lxml==5.3.0
Requires-Dist: mako==1.3.10
Requires-Dist: markupsafe==3.0.2
Requires-Dist: openedx-events==10.4.0
Requires-Dist: packaging==25.0
Requires-Dist: path==16.11.0
Requires-Dist: pbr==6.1.1
Requires-Dist: pillow==11.3.0
Requires-Dist: prompt-toolkit==3.0.51
Requires-Dist: psutil==7.0.0
Requires-Dist: pycparser==2.22
Requires-Dist: pyjwt[crypto]==2.10.1
Requires-Dist: pymongo==4.4.0
Requires-Dist: pynacl==1.5.0
Requires-Dist: pysrt==1.1.2
Requires-Dist: python-dateutil==2.9.0.post0
Requires-Dist: python-slugify==8.0.4
Requires-Dist: pytz==2025.2
Requires-Dist: pyyaml==6.0.2
Requires-Dist: requests==2.32.4
Requires-Dist: semantic-version==2.10.0
Requires-Dist: simplejson==3.20.1
Requires-Dist: six==1.17.0
Requires-Dist: soupsieve==2.7
Requires-Dist: sqlparse==0.5.3
Requires-Dist: stevedore==5.4.1
Requires-Dist: text-unidecode==1.3
Requires-Dist: typing-extensions==4.14.1
Requires-Dist: tzdata==2025.2
Requires-Dist: urllib3==2.2.3
Requires-Dist: vine==5.1.0
Requires-Dist: wcwidth==0.2.13
Requires-Dist: web-fragments==3.1.0
Requires-Dist: webob==1.8.9
Requires-Dist: xblock==5.2.0
Dynamic: author
Dynamic: author-email
Dynamic: classifier
Dynamic: description
Dynamic: description-content-type
Dynamic: license
Dynamic: license-file
Dynamic: requires-dist
Dynamic: summary
